playhdl/__init__.py
playhdl/cli.py
playhdl/log.py
playhdl/project.py
playhdl/runner.py
playhdl/settings.py
playhdl/templates/__init__.py
playhdl/templates/tb.sv
playhdl/templates/tb.v
playhdl/templates/tb_uvm12.sv
playhdl/tools.py
playhdl/utils.py
playhdl-0.2.1.dist-info/entry_points.txt
playhdl-0.2.1.dist-info/METADATA
playhdl-0.2.1.dist-info/LICENSE
playhdl-0.2.1.dist-info/WHEEL
playhdl-0.2.1.dist-info/RECORD
