Metadata-Version: 2.1
Name: playhdl
Version: 0.2.1
Summary: Tool to play with HDL (inspired by EdaPlayground)
Home-page: https://github.com/esynr3z/playhdl
License: MIT
Author: esynr3z
Author-email: esynr3z@gmail.com
Requires-Python: >=3.8,<4.0
Classifier: License :: OSI Approved :: MIT License
Classifier: Programming Language :: Python :: 3
Classifier: Programming Language :: Python :: 3.8
Classifier: Programming Language :: Python :: 3.9
Classifier: Programming Language :: Python :: 3.10
Classifier: Programming Language :: Python :: 3.11
Project-URL: Repository, https://github.com/esynr3z/playhdl
